typedmodel/__init__.py
typedmodel/compat.py
typedmodel/exceptions.py
typedmodel/models.py
typedmodel/utils.py
typedmodel-0.2.8.dist-info/METADATA
typedmodel-0.2.8.dist-info/WHEEL
typedmodel-0.2.8.dist-info/top_level.txt
typedmodel-0.2.8.dist-info/RECORD
