Metadata-Version: 2.1
Name: typedmodel
Version: 0.2.8
Summary: provide strict type checking for dataclass and pydantic model
Home-page: https://github.com/qiujiangkun/typedmodel
Author: Jiangkun QIU
Author-email: qjk2001@gmail.com
License: MIT
Platform: UNKNOWN
Classifier: License :: OSI Approved :: MIT License
Classifier: Programming Language :: Python :: 3
Classifier: Programming Language :: Python :: 3.7
Requires-Dist: beartype
